AUTHORS.rst
CONTRIBUTING.rst
HISTORY.rst
LICENSE
MANIFEST.in
README.rst
setup.cfg
setup.py
LowCostSmartFarmHub/LowCostSmartFarmHub.py
LowCostSmartFarmHub/__init__.py
LowCostSmartFarmHub/__main__.py
LowCostSmartFarmHub/actuator.py
LowCostSmartFarmHub/cli.py
LowCostSmartFarmHub/gateway.py
LowCostSmartFarmHub/nodeDevice.py
LowCostSmartFarmHub/sensor.py
LowCostSmartFarmHub.egg-info/PKG-INFO
LowCostSmartFarmHub.egg-info/SOURCES.txt
LowCostSmartFarmHub.egg-info/dependency_links.txt
LowCostSmartFarmHub.egg-info/entry_points.txt
LowCostSmartFarmHub.egg-info/requires.txt
LowCostSmartFarmHub.egg-info/top_level.txt
docs/Makefile
docs/authors.rst
docs/conf.py
docs/contributing.rst
docs/history.rst
docs/index.rst
docs/installation.rst
docs/make.bat
docs/readme.rst
docs/usage.rst
docs/user_doc/LowCostSmartFarmHub_terminology.rst
docs/user_doc/configuring_rpi_gateway.rst
docs/user_doc/working_with_rpi_gateway.rst
tests/__init__.py
tests/test_LowCostSmartFarmHub.py