Metadata-Version: 1.2
Name: LowCostSmartFarmHub
Version: 0.1.9
Summary: A gateway API for controlling and monitoring a wireless sensor network Digi-Xbee Modules
Home-page: https://github.com/itumeleng96/LowCostSmartFarmHub
Author: Joseph Malemela
Author-email: itukzz96@gmail.com
License: MIT license
Download-URL: https://github.com/itumeleng96/LowCostSmartFarmHub/archive/0.1.9.tar.gz
Keywords: LowCostSmartFarmHub
Platform: UNKNOWN
Classifier: Development Status :: 2 - Pre-Alpha
Classifier: Intended Audience :: Developers
Classifier: License :: OSI Approved :: MIT License
Classifier: Natural Language :: English
Classifier: Programming Language :: Python :: 3.6
Classifier: Programming Language :: Python :: 3.7
Classifier: Programming Language :: Python :: 3.8
Requires-Python: >=3.6
